StatusCode/__init__.py
StatusCode/status_code.py
StatusCode-1.0.0.dist-info/DESCRIPTION.rst
StatusCode-1.0.0.dist-info/METADATA
StatusCode-1.0.0.dist-info/RECORD
StatusCode-1.0.0.dist-info/WHEEL
StatusCode-1.0.0.dist-info/metadata.json
StatusCode-1.0.0.dist-info/top_level.txt
