Metadata-Version: 2.0
Name: StatusCode
Version: 1.0.0
Summary: Python Status Code based on ``kkconst``
Home-page: https://github.com/errorless/StatusCode
Author: Hackathon
Author-email: kimi.huang@brightcells.com
License: UNKNOWN
Keywords: StatusCode
Platform: UNKNOWN
Classifier: License :: OSI Approved :: BSD License
Classifier: Programming Language :: Python
Classifier: Programming Language :: Python :: 2
Classifier: Programming Language :: Python :: 2.5
Classifier: Programming Language :: Python :: 2.6
Classifier: Programming Language :: Python :: 2.7
Classifier: Programming Language :: Python :: 3
Classifier: Programming Language :: Python :: 3.2
Classifier: Programming Language :: Python :: 3.3
Classifier: Programming Language :: Python :: 3.4
Classifier: Topic :: Software Development :: Libraries :: Python Modules
Requires-Dist: kkconst
